SimSpecLib/__init__.py
SimSpecLib/simspec.py
SimSpecLib/extern/__init__.py
SimSpecLib/extern/blank.dat
SimSpecLib/extern/cosmics.py
SimSpecLib/extern/lacos_spec.cl
SimSpecLib/stdlib/bd25d4655.dat
SimSpecLib/stdlib/bd26d2606.dat
SimSpecLib/stdlib/bd28d4211.dat
SimSpecLib/stdlib/bd33d2642.dat
SimSpecLib/stdlib/feige110.dat
SimSpecLib/stdlib/feige34.dat
SimSpecLib/stdlib/feige56.dat
SimSpecLib/stdlib/feige66.dat
SimSpecLib/stdlib/feige66_vir.dat
SimSpecLib/stdlib/g191b2b.dat
SimSpecLib/stdlib/g24_9.dat
SimSpecLib/stdlib/gd108.dat
SimSpecLib/stdlib/gd153.dat
SimSpecLib/stdlib/gd248.dat
SimSpecLib/stdlib/gd71.dat
SimSpecLib/stdlib/grw70_8247.dat
SimSpecLib/stdlib/grw70d5824.dat
SimSpecLib/stdlib/hd19445.dat
SimSpecLib/stdlib/hd93521.dat
SimSpecLib/stdlib/hilt600.dat
SimSpecLib/stdlib/hr153.dat
SimSpecLib/stdlib/hr4468.dat
SimSpecLib/stdlib/hr5501.dat
SimSpecLib/stdlib/hr7596.dat
SimSpecLib/stdlib/hz4.dat
SimSpecLib/stdlib/hz44.dat
SimSpecLib/stdlib/ltt1020.dat
SimSpecLib/stdlib/ltt1788.dat
SimSpecLib/stdlib/ltt2415.dat
SimSpecLib/stdlib/ltt3218.dat
SimSpecLib/stdlib/ltt377.dat
SimSpecLib/stdlib/ltt3864.dat
SimSpecLib/stdlib/ltt4364.dat
SimSpecLib/stdlib/ltt4816.dat
SimSpecLib/stdlib/ltt6248.dat
SimSpecLib/stdlib/ltt7379.dat
SimSpecLib/stdlib/ltt7987.dat
SimSpecLib/stdlib/names.men
SimSpecLib/stdlib/pg1708_602.dat
SimSpecLib/stdlib/ross640.dat
SimSpecLib/stdlib/wolf1346.dat
simspeclib-2.3.0.3.dist-info/METADATA
simspeclib-2.3.0.3.dist-info/RECORD
simspeclib-2.3.0.3.dist-info/WHEEL
simspeclib-2.3.0.3.dist-info/top_level.txt
