Metadata-Version: 2.1
Name: simspeclib
Version: 2.3.0.3
Summary: SimSpec library. SIMplified SPECtrum reduction package for astronomy.
Home-page: http://astro.subhashbose.com/simspec
Author: Subhash Bose
Author-email: email@subhashbose.com
License: UNKNOWN
Platform: UNKNOWN
Classifier: Programming Language :: Python :: 2
Classifier: License :: Other/Proprietary License
Classifier: Operating System :: OS Independent
